fleetmix/__init__.py
fleetmix/__main__.py
fleetmix/api.py
fleetmix/app.py
fleetmix/core_types.py
fleetmix/gui.py
fleetmix/interfaces.py
fleetmix/registry.py
fleetmix/benchmarking/__init__.py
fleetmix/benchmarking/converters/__init__.py
fleetmix/benchmarking/converters/cvrp.py
fleetmix/benchmarking/converters/mcvrp.py
fleetmix/benchmarking/converters/vrp.py
fleetmix/benchmarking/datasets/__init__.py
fleetmix/benchmarking/models/__init__.py
fleetmix/benchmarking/models/instance_spec.py
fleetmix/benchmarking/models/models.py
fleetmix/benchmarking/parsers/__init__.py
fleetmix/benchmarking/parsers/cvrp.py
fleetmix/benchmarking/parsers/mcvrp.py
fleetmix/benchmarking/solvers/__init__.py
fleetmix/benchmarking/solvers/vrp_solver.py
fleetmix/clustering/__init__.py
fleetmix/clustering/generator.py
fleetmix/clustering/heuristics.py
fleetmix/config/__init__.py
fleetmix/config/loader.py
fleetmix/config/params.py
fleetmix/experiments/__init__.py
fleetmix/experiments/fleet_composition/__init__.py
fleetmix/experiments/fleet_composition/config.py
fleetmix/experiments/fleet_composition/fleet_templates.py
fleetmix/experiments/fleet_composition/metrics.py
fleetmix/experiments/fleet_composition/run_grid_mixed.py
fleetmix/experiments/reproduce_paper/__init__.py
fleetmix/experiments/reproduce_paper/fleet_composition_runner.py
fleetmix/experiments/reproduce_paper/mcvrp_runner.py
fleetmix/experiments/reproduce_paper/sensitivity_runner.py
fleetmix/experiments/reproduce_paper/utils.py
fleetmix/merging/__init__.py
fleetmix/merging/core.py
fleetmix/optimization/__init__.py
fleetmix/optimization/core.py
fleetmix/post_optimization/__init__.py
fleetmix/post_optimization/merge_phase.py
fleetmix/preprocess/__init__.py
fleetmix/preprocess/split_stop.py
fleetmix/utils/__init__.py
fleetmix/utils/cluster_conversion.py
fleetmix/utils/common.py
fleetmix/utils/coordinate_converter.py
fleetmix/utils/data_processing.py
fleetmix/utils/debug.py
fleetmix/utils/logging.py
fleetmix/utils/project_root.py
fleetmix-1.0.0.dist-info/licenses/LICENSE
fleetmix-1.0.0.dist-info/METADATA
fleetmix-1.0.0.dist-info/WHEEL
fleetmix-1.0.0.dist-info/entry_points.txt
fleetmix-1.0.0.dist-info/top_level.txt
fleetmix-1.0.0.dist-info/RECORD
