Metadata-Version: 2.4
Name: fleetmix
Version: 1.0.0
Summary: Fleet Size and Mix optimizer for heterogeneous fleets of multi-compartment vehicles
Requires-Python: >=3.12
License-File: LICENSE
Requires-Dist: numpy
Requires-Dist: pandas
Requires-Dist: scipy
Requires-Dist: matplotlib
Requires-Dist: seaborn
Requires-Dist: streamlit
Requires-Dist: plotly
Requires-Dist: scikit-learn
Requires-Dist: kmedoids
Requires-Dist: folium
Requires-Dist: streamlit-folium
Requires-Dist: haversine
Requires-Dist: gurobipy
Requires-Dist: geopy
Requires-Dist: jupyter
Requires-Dist: pulp
Requires-Dist: numba
Requires-Dist: cython
Requires-Dist: joblib
Requires-Dist: tqdm
Requires-Dist: openpyxl
Requires-Dist: pyvrp
Requires-Dist: rich
Requires-Dist: vrplib
Requires-Dist: typer[all]>=0.9.0
Requires-Dist: tabulate
Provides-Extra: test
Requires-Dist: pytest; extra == "test"
Requires-Dist: pytest-cov; extra == "test"
Requires-Dist: hypothesis; extra == "test"
Requires-Dist: pytest-xdist; extra == "test"
Requires-Dist: attrs>=23.1; extra == "test"
Provides-Extra: dev
Requires-Dist: mypy; extra == "dev"
Requires-Dist: ruff; extra == "dev"
Requires-Dist: types-tqdm; extra == "dev"
Requires-Dist: types-PyYAML; extra == "dev"
Requires-Dist: types-seaborn; extra == "dev"
Requires-Dist: pandas-stubs; extra == "dev"
Dynamic: license-file
